notify/__init__.py
notify/arguments.py
notify/compat.py
notify/conf.py
notify/console.py
notify/executor.py
notify/mailer.py
notify/notifier.py
notify/wizard.py
notify/utils/__init__.py
notify/utils/plaintext_keyring.py
notify/utils/terminalmsg.py
notify/utils/terminalsize.py
notify-0.3.1.dist-info/LICENSE
notify-0.3.1.dist-info/METADATA
notify-0.3.1.dist-info/WHEEL
notify-0.3.1.dist-info/entry_points.txt
notify-0.3.1.dist-info/top_level.txt
notify-0.3.1.dist-info/zip-safe
notify-0.3.1.dist-info/RECORD
